open_coscientist/__init__.py
open_coscientist/cache.py
open_coscientist/console.py
open_coscientist/constants.py
open_coscientist/generator.py
open_coscientist/llm.py
open_coscientist/mcp_client.py
open_coscientist/models.py
open_coscientist/prompts.py
open_coscientist/schemas.py
open_coscientist/state.py
open_coscientist/nodes/__init__.py
open_coscientist/nodes/evolve.py
open_coscientist/nodes/generate.py
open_coscientist/nodes/literature_review.py
open_coscientist/nodes/meta_review.py
open_coscientist/nodes/proximity.py
open_coscientist/nodes/ranking.py
open_coscientist/nodes/reflection.py
open_coscientist/nodes/review.py
open_coscientist/nodes/supervisor.py
open_coscientist/nodes/generation/__init__.py
open_coscientist/nodes/generation/coordinator.py
open_coscientist/nodes/generation/debate.py
open_coscientist/nodes/generation/literature_standard.py
open_coscientist/nodes/generation/standard.py
open_coscientist/nodes/generation/literature_tools/__init__.py
open_coscientist/nodes/generation/literature_tools/draft.py
open_coscientist/nodes/generation/literature_tools/validate.py
open_coscientist/prompts/evolution.md
open_coscientist/prompts/generation.md
open_coscientist/prompts/generation_after_debate.md
open_coscientist/prompts/generation_draft_with_tools.md
open_coscientist/prompts/generation_with_literature_review.md
open_coscientist/prompts/hypothesis_novelty_analysis.md
open_coscientist/prompts/hypothesis_validation_synthesis.md
open_coscientist/prompts/literature_review_paper_analysis.md
open_coscientist/prompts/literature_review_query_generation_pubmed.md
open_coscientist/prompts/literature_review_synthesis.md
open_coscientist/prompts/meta_review.md
open_coscientist/prompts/proximity.md
open_coscientist/prompts/ranking.md
open_coscientist/prompts/reflection_observations.md
open_coscientist/prompts/review.md
open_coscientist/prompts/review_batch.md
open_coscientist/prompts/supervisor.md
open_coscientist/tools/__init__.py
open_coscientist/tools/literature.py
open_coscientist-0.1.1.dist-info/licenses/LICENSE
open_coscientist-0.1.1.dist-info/METADATA
open_coscientist-0.1.1.dist-info/WHEEL
open_coscientist-0.1.1.dist-info/top_level.txt
open_coscientist-0.1.1.dist-info/RECORD
