Metadata-Version: 2.4
Name: open-coscientist
Version: 0.1.1
Summary: Open LangGraph-based framework for multi-agent research hypothesis generation, adapted from Google Research's AI Co-Scientist.
Author-email: Brandon Rose <brandon@jataware.com>
License: MIT License + Commons Clause
Project-URL: Homepage, https://github.com/jataware/open-coscientist
Project-URL: Documentation, https://github.com/jataware/open-coscientist#readme
Project-URL: Repository, https://github.com/jataware/open-coscientist
Keywords: ai,research,hypothesis,langgraph,llm
Classifier: Development Status :: 3 - Alpha
Classifier: Intended Audience :: Science/Research
Classifier: Programming Language :: Python :: 3.10
Classifier: Programming Language :: Python :: 3.11
Classifier: Programming Language :: Python :: 3.12
Requires-Python: >=3.10
License-File: LICENSE
Requires-Dist: langgraph~=1.0.6
Requires-Dist: langchain-core~=1.2.7
Requires-Dist: langchain-mcp-adapters>=0.2.1
Requires-Dist: langsmith~=0.6.2
Requires-Dist: litellm~=1.80.16
Requires-Dist: typing-extensions~=4.15.0
Requires-Dist: rich~=14.2.0
Requires-Dist: jsonschema~=4.26.0
Provides-Extra: dev
Requires-Dist: pytest~=9.0.2; extra == "dev"
Requires-Dist: pytest-asyncio~=1.3.0; extra == "dev"
Requires-Dist: black~=25.12.0; extra == "dev"
Requires-Dist: ruff~=0.14.11; extra == "dev"
Requires-Dist: mypy~=1.19.1; extra == "dev"
Requires-Dist: python-dotenv~=1.2.1; extra == "dev"
Dynamic: license-file
